{
    "sec_cik": "0000898173",
    "sec_company_name": "O REILLY AUTOMOTIVE INC (Filer)",
    "document_type": "8K",
    "sec_form_header": "Form 8-K",
    "sec_period_of_report": "20220103",
    "sec_filing_date": "20220103",
    "sec_changed_date": "20220103",
    "sec_accepted_date": "20220103163045",
    "sec_index_url": "https://www.sec.gov//Archives/edgar/data/898173/000089817322000002/0000898173-22-000002-index.htm",
    "sec_url": "https://www.sec.gov//Archives/edgar/data/898173/000089817322000002/0000898173-22-000002.txt",
    "metadata_file_name": "C:\Users\aaron\OneDrive\Desktop\homework\finance2\SEC-EDGAR-text\output_files_examples\batch_0011\003\ORLY_0000898173_8K_20220103_8-K_metadata.json",
    "original_file_name": "file was not saved locally",
    "original_file_size": "46323 chars",
    "document_group": "8-K",
    "section_name": "8-K",
    "section_n_characters": 2947,
    "endpoints": [
        "xml version='1.0' encoding='UTF-8'?      ",
        "​"
    ],
    "extraction_method": "xbrl",
    "warnings": [],
    "company_description": "ORLY",
    "output_file": "C:\Users\aaron\OneDrive\Desktop\homework\finance2\SEC-EDGAR-text\output_files_examples\batch_0011\003\ORLY_0000898173_8K_20220103_8-K_excerpt.txt",
    "time_elapsed": 0.0,
    "batch_number": 11,
    "batch_signature": "",
    "batch_start_time": "2023-04-17 00:20:00.439699",
    "batch_machine_id": "DESKTOP-BTCJU5K",
    "section_end_time": "2023-04-17 00:29:55.556865"
}