{
    "sec_cik": "0000037634",
    "sec_company_name": "FLORIDA POWER & LIGHT CO (Filer)",
    "document_type": "8K",
    "sec_form_header": "Form 8-K",
    "sec_period_of_report": "20210111",
    "sec_filing_date": "20210111",
    "sec_changed_date": "20210111",
    "sec_accepted_date": "20210111161334",
    "sec_index_url": "https://www.sec.gov//Archives/edgar/data/753308/000075330821000003/0000753308-21-000003-index.htm",
    "sec_url": "https://www.sec.gov//Archives/edgar/data/753308/000075330821000003/0000753308-21-000003.txt",
    "metadata_file_name": "C:\Users\aaron\OneDrive\Desktop\homework\finance2\SEC-EDGAR-text\output_files_examples\batch_0010\004\NEE_0000037634_8K_20210111_8-K_metadata.json",
    "original_file_name": "file was not saved locally",
    "original_file_size": "64048 chars",
    "document_group": "8-K",
    "section_name": "8-K",
    "section_n_characters": 14846,
    "endpoints": [
        "xml version='1.0' ? nee-20210111",
        "5"
    ],
    "extraction_method": "xbrl",
    "warnings": [],
    "company_description": "NEE",
    "output_file": "C:\Users\aaron\OneDrive\Desktop\homework\finance2\SEC-EDGAR-text\output_files_examples\batch_0010\004\NEE_0000037634_8K_20210111_8-K_excerpt.txt",
    "time_elapsed": 0.0,
    "batch_number": 10,
    "batch_signature": "",
    "batch_start_time": "2023-04-16 23:51:33.991322",
    "batch_machine_id": "DESKTOP-BTCJU5K",
    "section_end_time": "2023-04-17 00:11:29.239689"
}