{
    "sec_cik": "0000007084",
    "sec_company_name": "ARCHER DANIELS MIDLAND CO (Filer)",
    "document_type": "8K",
    "sec_form_header": "Form 8-K",
    "sec_period_of_report": "20160202",
    "sec_filing_date": "20160202",
    "sec_changed_date": "20160202",
    "sec_accepted_date": "20160202104453",
    "sec_index_url": "https://www.sec.gov//Archives/edgar/data/7084/000000708416000039/0000007084-16-000039-index.htm",
    "sec_url": "https://www.sec.gov//Archives/edgar/data/7084/000000708416000039/0000007084-16-000039.txt",
    "metadata_file_name": "C:\Users\aaron\OneDrive\Desktop\homework\finance2\SEC-EDGAR-text\output_files_examples\batch_0005\002\ADM_0000007084_8K_20160202_8-K_metadata.json",
    "original_file_name": "file was not saved locally",
    "original_file_size": "25948 chars",
    "document_group": "8-K",
    "section_name": "8-K",
    "section_n_characters": 2384,
    "endpoints": [
        "8-K   ",
        "99.1 Press Release dated February 2, 2016"
    ],
    "extraction_method": "html",
    "warnings": [],
    "company_description": "ADM",
    "output_file": "C:\Users\aaron\OneDrive\Desktop\homework\finance2\SEC-EDGAR-text\output_files_examples\batch_0005\002\ADM_0000007084_8K_20160202_8-K_excerpt.txt",
    "time_elapsed": 0.0,
    "batch_number": 5,
    "batch_signature": "",
    "batch_start_time": "2023-04-16 21:41:24.213091",
    "batch_machine_id": "DESKTOP-BTCJU5K",
    "section_end_time": "2023-04-16 21:47:43.885241"
}