{
    "sec_cik": "0000081033",
    "sec_company_name": "PUBLIC SERVICE ELECTRIC & GAS CO (Filer)",
    "document_type": "EX99",
    "sec_form_header": "Form 8-K",
    "sec_period_of_report": "20210226",
    "sec_filing_date": "20210226",
    "sec_changed_date": "20210226",
    "sec_accepted_date": "20210226090114",
    "sec_index_url": "https://www.sec.gov//Archives/edgar/data/788784/000119312521058671/0001193125-21-058671-index.htm",
    "sec_url": "https://www.sec.gov//Archives/edgar/data/788784/000119312521058671/0001193125-21-058671.txt",
    "metadata_file_name": "C:\Users\aaron\OneDrive\Desktop\homework\finance2\SEC-EDGAR-text\output_files_examples\batch_0010\002\PEG_0000081033_EX99_20210226_EX-99_metadata.json",
    "original_file_name": "",
    "original_file_size": "371723 chars",
    "document_group": "EX-99",
    "section_name": "EX-99",
    "section_n_characters": 27163,
    "endpoints": [
        "EX-99   ",
        "Income tax effect calculated at a combined leveraged lease effective tax rate."
    ],
    "extraction_method": "html",
    "warnings": [],
    "company_description": "PEG",
    "output_file": "C:\Users\aaron\OneDrive\Desktop\homework\finance2\SEC-EDGAR-text\output_files_examples\batch_0010\002\PEG_0000081033_EX99_20210226_EX-99_excerpt.txt",
    "time_elapsed": 0.2,
    "batch_number": 10,
    "batch_signature": "",
    "batch_start_time": "2023-04-16 23:51:33.991322",
    "batch_machine_id": "DESKTOP-BTCJU5K",
    "section_end_time": "2023-04-17 00:01:56.208635"
}