{
    "sec_cik": "0000350698",
    "sec_company_name": "AUTONATION, INC. (Filer)",
    "document_type": "EX991",
    "sec_form_header": "Form 8-K",
    "sec_period_of_report": "20150116",
    "sec_filing_date": "20150116",
    "sec_changed_date": "20150116",
    "sec_accepted_date": "20150116171004",
    "sec_index_url": "https://www.sec.gov//Archives/edgar/data/350698/000035069815000026/0000350698-15-000026-index.htm",
    "sec_url": "https://www.sec.gov//Archives/edgar/data/350698/000035069815000026/0000350698-15-000026.txt",
    "metadata_file_name": "C:\Users\aaron\OneDrive\Desktop\homework\finance2\SEC-EDGAR-text\output_files_examples\batch_0004\002\AN_0000350698_EX991_20150116_EX-99_metadata.json",
    "original_file_name": "",
    "original_file_size": "9988 chars",
    "document_group": "EX-99",
    "section_name": "EX-99",
    "section_n_characters": 3461,
    "endpoints": [
        "EX99.1 PRESS RELEASE   ",
        "Please visit investors.autonation.com, www.autonation.com, www.twitter.com/autonation, www.twitter.com/CEOMikeJackson, www.facebook.com/autonation, and www.facebook.com/CEOMikeJackson, where AutoNation discloses additional information about the Company, its business, and its results of operations."
    ],
    "extraction_method": "html",
    "warnings": [],
    "company_description": "AN",
    "output_file": "C:\Users\aaron\OneDrive\Desktop\homework\finance2\SEC-EDGAR-text\output_files_examples\batch_0004\002\AN_0000350698_EX991_20150116_EX-99_excerpt.txt",
    "time_elapsed": 0.0,
    "batch_number": 4,
    "batch_signature": "",
    "batch_start_time": "2023-04-16 21:15:41.037609",
    "batch_machine_id": "DESKTOP-BTCJU5K",
    "section_end_time": "2023-04-16 21:19:37.459727"
}