{
    "sec_cik": "0000823768",
    "sec_company_name": "WASTE MANAGEMENT INC (Filer)",
    "document_type": "10KA",
    "sec_form_header": "Form 10-K/A",
    "sec_period_of_report": "20211231",
    "sec_filing_date": "20220329",
    "sec_changed_date": "20220329",
    "sec_accepted_date": "20220329151735",
    "sec_index_url": "https://www.sec.gov//Archives/edgar/data/823768/000155837022004593/0001558370-22-004593-index.htm",
    "sec_url": "https://www.sec.gov//Archives/edgar/data/823768/000155837022004593/0001558370-22-004593.txt",
    "metadata_file_name": "C:\Users\aaron\OneDrive\Desktop\homework\finance2\SEC-EDGAR-text\output_files_examples\batch_0013\001\WM_0000823768_10KA_20211231_Item1_failure.json",
    "original_file_name": "",
    "original_file_size": "68069 chars",
    "document_group": "10-K",
    "section_name": "Item1",
    "section_n_characters": null,
    "endpoints": [
        "na",
        "na"
    ],
    "extraction_method": "xbrl",
    "warnings": [
        "Extraction did not work for HTML file"
    ],
    "company_description": "WM",
    "output_file": null,
    "time_elapsed": 0.0,
    "batch_number": 13,
    "batch_signature": "",
    "batch_start_time": "2023-04-27 17:30:01.551160",
    "batch_machine_id": "DESKTOP-BTCJU5K",
    "section_end_time": "2023-04-27 17:33:56.032446"
}